setup.py
hiwi/__init__.py
hiwi/hiwi.py
hiwi/hiwierrors.py
hiwi/main.py
hiwi.egg-info/PKG-INFO
hiwi.egg-info/SOURCES.txt
hiwi.egg-info/dependency_links.txt
hiwi.egg-info/entry_points.txt
hiwi.egg-info/not-zip-safe
hiwi.egg-info/requires.txt
hiwi.egg-info/top_level.txt