Metadata-Version: 1.0
Name: hiwi
Version: 0.1
Summary: Integrate or share otree experiments with ease
Home-page: http://github.com/chkgk/hiwi
Author: Christian König genannt Kersting
Author-email: christian.koenig@awi.uni-heidelberg.de
License: MIT
Platform: UNKNOWN
